[
 {
   "Date": "2020/01/02",
   "Year": 2020,
   "Algerian_dinar": 119.1599,
   "Australian_dollar": 1.427959446,
   "Botswana_pula": 10.70663812,
   "Brazilian_real": 4.0207,
   "Brunei_dollar": 1.3468,
   "Canadian_dollar": 1.2992,
   "Chilean_peso": 758.49,
   "Chinese_yuan": 6.967,
   "Colombian_peso": 3277.14,
   "Czech_koruna": 22.702,
   "Danish_krone": 6.6755,
   "Euro": 0.893415528,
   "Indian_rupee": 71.3429,
   "Israeli_New_Shekel": 3.452,
   "Japanese_yen": 109.12,
   "Korean_won": 1157.8,
   "Kuwaiti_dinar": 0.30305,
   "Malaysian_ringgit": 4.0865,
   "Mauritian_rupee": 36.4983,
   "Mexican_peso": 18.8817,
   "New_Zealand_dollar": 1.493205913,
   "Norwegian_krone": 8.7919,
   "Omani_rial": 0.3845,
   "Peruvian_sol": 3.301,
   "Philippine_peso": 50.802,
   "Polish_zloty": 3.8,
   "Qatari_riyal": 3.64,
   "Russian_ruble": 61.234,
   "Saudi_Arabian_riyal": 3.75,
   "Singapore_dollar": 1.3468,
   "South_African_rand": 14.02745,
   "Swedish_krona": 9.3341,
   "Swiss_franc": 0.97365,
   "Thai_baht": 30.11,
   "Trinidadian_dollar": 6.7624,
   "UAE_dirham": 3.6725,
   "UK_pound": 0.757661856,
   "US_dollar": 1,
   "Uruguayan_peso": 37.194
 },
 {
   "Date": "2020/02/03",
   "Year": 2020,
   "Algerian_dinar": 119.7394,
   "Australian_dollar": 1.493428913,
   "Botswana_pula": 10.94091904,
   "Brazilian_real": 4.2469,
   "Brunei_dollar": 1.3681,
   "Canadian_dollar": 1.3275,
   "Chilean_peso": 799.11,
   "Chinese_yuan": 7.0213,
   "Colombian_peso": 3423.24,
   "Czech_koruna": 22.75,
   "Danish_krone": 6.753,
   "Euro": 0.903668896,
   "Indian_rupee": 71.5803,
   "Israeli_New_Shekel": 3.446,
   "Japanese_yen": 108.52,
   "Korean_won": 1187.8,
   "Kuwaiti_dinar": 0.3038,
   "Malaysian_ringgit": 4.1155,
   "Mauritian_rupee": 36.8595,
   "Mexican_peso": 18.6797,
   "New_Zealand_dollar": 1.547029703,
   "Norwegian_krone": 9.2707,
   "Omani_rial": 0.3845,
   "Peruvian_sol": 3.372,
   "Philippine_peso": 50.855,
   "Polish_zloty": 3.8864,
   "Qatari_riyal": 3.64,
   "Russian_ruble": 63.9091,
   "Saudi_Arabian_riyal": 3.75,
   "Singapore_dollar": 1.3681,
   "South_African_rand": 14.8794,
   "Swedish_krona": 9.6347,
   "Swiss_franc": 0.96475,
   "Thai_baht": 31.191,
   "Trinidadian_dollar": 6.7382,
   "UAE_dirham": 3.6725,
   "UK_pound": 0.765960706,
   "US_dollar": 1,
   "Uruguayan_peso": 37.568
 },
 {
   "Date": "2020/03/02",
   "Year": 2020,
   "Algerian_dinar": 119.8396,
   "Australian_dollar": 1.533272002,
   "Botswana_pula": 11.17318436,
   "Brazilian_real": 4.494,
   "Brunei_dollar": 1.3905,
   "Canadian_dollar": 1.3356,
   "Chilean_peso": 818.32,
   "Chinese_yuan": 6.9623,
   "Colombian_peso": 3539.86,
   "Czech_koruna": 22.952,
   "Danish_krone": 6.7191,
   "Euro": 0.899118864,
   "Indian_rupee": 72.242,
   "Israeli_New_Shekel": 3.461,
   "Japanese_yen": 107.67,
   "Korean_won": 1215.3,
   "Kuwaiti_dinar": 0.3056,
   "Malaysian_ringgit": 4.2015,
   "Mauritian_rupee": 37.4136,
   "Mexican_peso": 19.6985,
   "New_Zealand_dollar": 1.607975559,
   "Norwegian_krone": 9.3547,
   "Omani_rial": 0.3845,
   "Peruvian_sol": 3.441,
   "Philippine_peso": 50.897,
   "Polish_zloty": 3.9023,
   "Qatari_riyal": 3.64,
   "Russian_ruble": 66.3274,
   "Saudi_Arabian_riyal": 3.75,
   "Singapore_dollar": 1.3905,
   "South_African_rand": 15.6649,
   "Swedish_krona": 9.517,
   "Swiss_franc": 0.9568,
   "Thai_baht": 31.361,
   "Trinidadian_dollar": 6.7514,
   "UAE_dirham": 3.6725,
   "UK_pound": 0.782227785,
   "US_dollar": 1,
   "Uruguayan_peso": 39.191
 },
 {
   "Date": "2020/04/01",
   "Year": 2020,
   "Algerian_dinar": 125.1408,
   "Australian_dollar": 1.63291966,
   "Botswana_pula": 11.9760479,
   "Brazilian_real": 5.2399,
   "Brunei_dollar": 1.4244,
   "Canadian_dollar": 1.4217,
   "Chilean_peso": 852.03,
   "Chinese_yuan": 7.1041,
   "Colombian_peso": 4054.54,
   "Czech_koruna": 25.039,
   "Danish_krone": 6.8253,
   "Euro": 0.914411119,
   "Indian_rupee": 75.3859,
   "Israeli_New_Shekel": 3.556,
   "Japanese_yen": 107.58,
   "Korean_won": 1220,
   "Kuwaiti_dinar": 0.3092,
   "Malaysian_ringgit": 4.3275,
   "Mauritian_rupee": 39.3685,
   "Mexican_peso": 24.4918,
   "New_Zealand_dollar": 1.677852349,
   "Norwegian_krone": 10.304,
   "Omani_rial": 0.3845,
   "Peruvian_sol": 3.455,
   "Philippine_peso": 50.78,
   "Polish_zloty": 4.1701,
   "Qatari_riyal": 3.64,
   "Russian_ruble": 77.7325,
   "Saudi_Arabian_riyal": 3.75,
   "Singapore_dollar": 1.4244,
   "South_African_rand": 17.989,
   "Swedish_krona": 9.9638,
   "Swiss_franc": 0.9654,
   "Thai_baht": 32.918,
   "Trinidadian_dollar": 6.7437,
   "UAE_dirham": 3.6725,
   "UK_pound": 0.807754443,
   "US_dollar": 1,
   "Uruguayan_peso": 44.003
 },
 {
   "Date": "2020/05/01",
   "Year": 2020,
   "Algerian_dinar": 128.5773,
   "Australian_dollar": 1.54822728,
   "Botswana_pula": 12.25490196,
   "Brazilian_real": 5.5811,
   "Brunei_dollar": 1.4172,
   "Canadian_dollar": 1.4085,
   "Chilean_peso": 837.92,
   "Chinese_yuan": 7.0915,
   "Colombian_peso": 3932.72,
   "Czech_koruna": 24.785,
   "Danish_krone": 6.8198,
   "Euro": 0.913909706,
   "Indian_rupee": 75.7902,
   "Israeli_New_Shekel": 3.491,
   "Japanese_yen": 107.1,
   "Korean_won": 1218.5,
   "Kuwaiti_dinar": 0.30855,
   "Malaysian_ringgit": 4.3385,
   "Mauritian_rupee": 40.1895,
   "Mexican_peso": 24.3812,
   "New_Zealand_dollar": 1.638806949,
   "Norwegian_krone": 10.3528,
   "Omani_rial": 0.3845,
   "Peruvian_sol": 3.383,
   "Philippine_peso": 50.444,
   "Polish_zloty": 4.1646,
   "Qatari_riyal": 3.64,
   "Russian_ruble": 73.9719,
   "Saudi_Arabian_riyal": 3.75,
   "Singapore_dollar": 1.4172,
   "South_African_rand": 18.7056,
   "Swedish_krona": 9.9052,
   "Swiss_franc": 0.9647,
   "Thai_baht": 32.381,
   "Trinidadian_dollar": 6.7457,
   "UAE_dirham": 3.6725,
   "UK_pound": 0.796717524,
   "US_dollar": 1,
   "Uruguayan_peso": 42.744
 },
 {
   "Date": "2020/06/01",
   "Year": 2020,
   "Algerian_dinar": 128.4895,
   "Australian_dollar": 1.469939732,
   "Botswana_pula": 11.79245283,
   "Brazilian_real": 5.3633,
   "Brunei_dollar": 1.4061,
   "Canadian_dollar": 1.363,
   "Chilean_peso": 806.32,
   "Chinese_yuan": 7.1161,
   "Colombian_peso": 3718.82,
   "Czech_koruna": 24.163,
   "Danish_krone": 6.6709,
   "Euro": 0.899604174,
   "Indian_rupee": 75.4792,
   "Israeli_New_Shekel": 3.509,
   "Japanese_yen": 107.75,
   "Korean_won": 1237.6,
   "Kuwaiti_dinar": 0.30815,
   "Malaysian_ringgit": 4.323,
   "Mauritian_rupee": 40.1242,
   "Mexican_peso": 22.0168,
   "New_Zealand_dollar": 1.592356688,
   "Norwegian_krone": 9.5577,
   "Omani_rial": 0.3845,
   "Peruvian_sol": 3.421,
   "Philippine_peso": 50.585,
   "Polish_zloty": 3.968,
   "Qatari_riyal": 3.64,
   "Russian_ruble": 69.7114,
   "Saudi_Arabian_riyal": 3.75,
   "Singapore_dollar": 1.4084,
   "South_African_rand": 17.47615,
   "Swedish_krona": 9.3789,
   "Swiss_franc": 0.96185,
   "Thai_baht": 31.734,
   "Trinidadian_dollar": 6.7351,
   "UAE_dirham": 3.6725,
   "UK_pound": 0.807689201,
   "US_dollar": 1,
   "Uruguayan_peso": 43.312
 },
 {
   "Date": "2020/07/01",
   "Year": 2020,
   "Algerian_dinar": 129.1417,
   "Australian_dollar": 1.450326323,
   "Botswana_pula": 11.68224299,
   "Brazilian_real": 5.3646,
   "Brunei_dollar": 1.3939,
   "Canadian_dollar": 1.3586,
   "Chilean_peso": 821.23,
   "Chinese_yuan": 7.063,
   "Colombian_peso": 3756.28,
   "Czech_koruna": 23.81,
   "Danish_krone": 6.6543,
   "Euro": 0.892857143,
   "Indian_rupee": 75.5813,
   "Israeli_New_Shekel": 3.454,
   "Japanese_yen": 107.69,
   "Korean_won": 1198.5,
   "Kuwaiti_dinar": 0.3078,
   "Malaysian_ringgit": 4.2815,
   "Mauritian_rupee": 40.2826,
   "Mexican_peso": 22.8078,
   "New_Zealand_dollar": 1.547508511,
   "Norwegian_krone": 9.6193,
   "Omani_rial": 0.3845,
   "Peruvian_sol": 3.533,
   "Philippine_peso": 49.79,
   "Polish_zloty": 3.9591,
   "Qatari_riyal": 3.64,
   "Russian_ruble": 70.4413,
   "Saudi_Arabian_riyal": 3.75,
   "Singapore_dollar": 1.3939,
   "South_African_rand": 17.2704,
   "Swedish_krona": 9.3164,
   "Swiss_franc": 0.94735,
   "Thai_baht": 30.954,
   "Trinidadian_dollar": 6.7141,
   "UAE_dirham": 3.6725,
   "UK_pound": 0.806094071,
   "US_dollar": 1,
   "Uruguayan_peso": 42.175
 },
 {
   "Date": "2020/08/03",
   "Year": 2020,
   "Algerian_dinar": 128.5118,
   "Australian_dollar": 1.402131239,
   "Botswana_pula": 11.61440186,
   "Brazilian_real": 5.3069,
   "Brunei_dollar": 1.376,
   "Canadian_dollar": 1.3372,
   "Chilean_peso": 757.06,
   "Chinese_yuan": 6.9758,
   "Colombian_peso": 3733.08,
   "Czech_koruna": 22.451,
   "Danish_krone": 6.3505,
   "Euro": 0.852805731,
   "Indian_rupee": 74.9789,
   "Israeli_New_Shekel": 3.415,
   "Japanese_yen": 106.2,
   "Korean_won": 1189.1,
   "Kuwaiti_dinar": 0.30585,
   "Malaysian_ringgit": 4.2335,
   "Mauritian_rupee": 39.963,
   "Mexican_peso": 22.614,
   "New_Zealand_dollar": 1.507613448,
   "Norwegian_krone": 9.1411,
   "Omani_rial": 0.3845,
   "Peruvian_sol": 3.538,
   "Philippine_peso": 49.114,
   "Polish_zloty": 3.7499,
   "Qatari_riyal": 3.64,
   "Russian_ruble": 74.1586,
   "Saudi_Arabian_riyal": 3.75,
   "Singapore_dollar": 1.376,
   "South_African_rand": 17.26765,
   "Swedish_krona": 8.7839,
   "Swiss_franc": 0.91815,
   "Thai_baht": 31.227,
   "Trinidadian_dollar": 6.7409,
   "UAE_dirham": 3.6725,
   "UK_pound": 0.768403258,
   "US_dollar": 1,
   "Uruguayan_peso": 42.655
 },
 {
   "Date": "2020/09/01",
   "Year": 2020,
   "Algerian_dinar": 127.7242,
   "Australian_dollar": 1.349163519,
   "Botswana_pula": 11.49425287,
   "Brazilian_real": 5.3726,
   "Brunei_dollar": 1.357,
   "Canadian_dollar": 1.3055,
   "Chilean_peso": 776.46,
   "Chinese_yuan": 6.8185,
   "Colombian_peso": 3745.41,
   "Czech_koruna": 21.882,
   "Danish_krone": 6.2096,
   "Euro": 0.83423709,
   "Indian_rupee": 72.8204,
   "Israeli_New_Shekel": 3.353,
   "Japanese_yen": 105.87,
   "Korean_won": 1183.3,
   "Kuwaiti_dinar": 0.3051,
   "Malaysian_ringgit": 4.1475,
   "Mauritian_rupee": 39.7681,
   "Mexican_peso": 21.7445,
   "New_Zealand_dollar": 1.47972773,
   "Norwegian_krone": 8.7076,
   "Omani_rial": 0.3845,
   "Peruvian_sol": 3.527,
   "Philippine_peso": 48.483,
   "Polish_zloty": 3.6707,
   "Qatari_riyal": 3.64,
   "Russian_ruble": 73.5849,
   "Saudi_Arabian_riyal": 3.75,
   "Singapore_dollar": 1.357,
   "South_African_rand": 16.66,
   "Swedish_krona": 8.6191,
   "Swiss_franc": 0.90415,
   "Thai_baht": 30.989,
   "Trinidadian_dollar": 6.7225,
   "UAE_dirham": 3.6725,
   "UK_pound": 0.742473178,
   "US_dollar": 1,
   "Uruguayan_peso": 42.502
 },
 {
   "Date": "2020/10/01",
   "Year": 2020,
   "Algerian_dinar": 129.1067,
   "Australian_dollar": 1.391207568,
   "Botswana_pula": 11.52073733,
   "Brazilian_real": 5.6435,
   "Brunei_dollar": 1.3634,
   "Canadian_dollar": 1.3292,
   "Chilean_peso": 788.15,
   "Chinese_yuan": 6.7153,
   "Colombian_peso": 3865.47,
   "Czech_koruna": 22.895,
   "Danish_krone": 6.3326,
   "Euro": 0.850918993,
   "Indian_rupee": 73.3834,
   "Israeli_New_Shekel": 3.427,
   "Japanese_yen": 105.54,
   "Korean_won": 1169.5,
   "Kuwaiti_dinar": 0.30605,
   "Malaysian_ringgit": 4.148,
   "Mauritian_rupee": 40.0354,
   "Mexican_peso": 21.9562,
   "New_Zealand_dollar": 1.510802236,
   "Norwegian_krone": 9.2812,
   "Omani_rial": 0.3845,
   "Peruvian_sol": 3.602,
   "Philippine_peso": 48.422,
   "Polish_zloty": 3.8513,
   "Qatari_riyal": 3.64,
   "Russian_ruble": 77.2774,
   "Saudi_Arabian_riyal": 3.75,
   "Singapore_dollar": 1.3634,
   "South_African_rand": 16.6079,
   "Swedish_krona": 8.9396,
   "Swiss_franc": 0.91815,
   "Thai_baht": 31.588,
   "Trinidadian_dollar": 6.728,
   "UAE_dirham": 3.6725,
   "UK_pound": 0.779028551,
   "US_dollar": 1,
   "Uruguayan_peso": 42.533
 },
 {
   "Date": "2020/11/02",
   "Year": 2020,
   "Algerian_dinar": 129.5189,
   "Australian_dollar": 1.428571429,
   "Botswana_pula": 11.41552511,
   "Brazilian_real": 5.6889,
   "Brunei_dollar": 1.3672,
   "Canadian_dollar": 1.3257,
   "Chilean_peso": 771.92,
   "Chinese_yuan": 6.6976,
   "Colombian_peso": 3858.56,
   "Czech_koruna": 23.284,
   "Danish_krone": 6.3899,
   "Euro": 0.858221765,
   "Indian_rupee": 74.322,
   "Israeli_New_Shekel": 3.4,
   "Japanese_yen": 104.74,
   "Korean_won": 1130.4,
   "Kuwaiti_dinar": 0.30615,
   "Malaysian_ringgit": 4.155,
   "Mauritian_rupee": 40.2005,
   "Mexican_peso": 21.1555,
   "New_Zealand_dollar": 1.516530179,
   "Norwegian_krone": 9.5372,
   "Omani_rial": 0.3845,
   "Peruvian_sol": 3.6,
   "Philippine_peso": 48.396,
   "Polish_zloty": 3.9557,
   "Qatari_riyal": 3.64,
   "Russian_ruble": 80.5749,
   "Saudi_Arabian_riyal": 3.75,
   "Singapore_dollar": 1.3672,
   "South_African_rand": 16.26815,
   "Swedish_krona": 8.93,
   "Swiss_franc": 0.9173,
   "Thai_baht": 31.159,
   "Trinidadian_dollar": 6.7338,
   "UAE_dirham": 3.6725,
   "UK_pound": 0.774773379,
   "US_dollar": 1,
   "Uruguayan_peso": 42.826
 },
 {
   "Date": "2020/12/01",
   "Year": 2020,
   "Algerian_dinar": 129.4812,
   "Australian_dollar": 1.357220413,
   "Botswana_pula": 11.0864745,
   "Brazilian_real": 5.2783,
   "Brunei_dollar": 1.3392,
   "Canadian_dollar": 1.2952,
   "Chilean_peso": 767.29,
   "Chinese_yuan": 6.5621,
   "Colombian_peso": 3591.84,
   "Czech_koruna": 21.922,
   "Danish_krone": 6.22,
   "Euro": 0.835561497,
   "Indian_rupee": 73.5083,
   "Israeli_New_Shekel": 3.304,
   "Japanese_yen": 104.26,
   "Korean_won": 1104.9,
   "Kuwaiti_dinar": 0.30505,
   "Malaysian_ringgit": 4.078,
   "Mauritian_rupee": 39.9961,
   "Mexican_peso": 20.0508,
   "New_Zealand_dollar": 1.422879909,
   "Norwegian_krone": 8.8593,
   "Omani_rial": 0.3845,
   "Peruvian_sol": 3.602,
   "Philippine_peso": 48.085,
   "Polish_zloty": 3.7367,
   "Qatari_riyal": 3.64,
   "Russian_ruble": 76.3203,
   "Saudi_Arabian_riyal": 3.75,
   "Singapore_dollar": 1.3392,
   "South_African_rand": 15.3367,
   "Swedish_krona": 8.5233,
   "Swiss_franc": 0.9058,
   "Thai_baht": 30.263,
   "Trinidadian_dollar": 6.7706,
   "UAE_dirham": 3.6725,
   "UK_pound": 0.750412727,
   "US_dollar": 1,
   "Uruguayan_peso": 42.39
 }
]